{
 "skippableComposables": 3,
 "restartableComposables": 4,
 "readonlyComposables": 0,
 "totalComposables": 4,
 "restartGroups": 4,
 "totalGroups": 10,
 "staticArguments": 3,
 "certainArguments": 4,
 "knownStableArguments": 38,
 "knownUnstableArguments": 1,
 "unknownStableArguments": 1,
 "totalArguments": 40,
 "markedStableClasses": 0,
 "inferredStableClasses": 0,
 "inferredUnstableClasses": 0,
 "inferredUncertainClasses": 0,
 "effectivelyStableClasses": 0,
 "totalClasses": 0,
 "memoizedLambdas": 2,
 "singletonLambdas": 0,
 "singletonComposableLambdas": 0,
 "composableLambdas": 1,
 "totalLambdas": 2
}